filtertext/RemoveDuplicatedLinesTextFilter.py
filtertext/RemoveWhitespaceLinesTextFilter.py
filtertext/TextFilter.py
filtertext/__init__.py
filtertext-1.0.1.data/scripts/filter_text.py
filtertext-1.0.1.dist-info/LICENSE.md
filtertext-1.0.1.dist-info/METADATA
filtertext-1.0.1.dist-info/WHEEL
filtertext-1.0.1.dist-info/top_level.txt
filtertext-1.0.1.dist-info/RECORD
