Metadata-Version: 2.1
Name: filtertext
Version: 1.0.1
Summary: Filter text and save result to file or print to output!
Home-page: http://github.com/michagrandel/filtertext/
Download-URL: https://github.com/michagrandel/filtertext/releases/download/v1.0.1/filtertext-1.0.1-py3-none-any.whl
Author: Micha Grandel
Author-email: hello@michagrandel.de
License: Apache 2.0 License
Platform: any
Classifier: Programming Language :: Python
Classifier: Development Status :: 4 - Beta
Classifier: Natural Language :: English
Classifier: License :: OSI Approved :: Apache Software License
Classifier: Operating System :: OS Independent
License-File: LICENSE.md
